k7eeel/__init__.py
k7eeel/loader.py
k7eeel-0.1.0.dist-info/METADATA
k7eeel-0.1.0.dist-info/WHEEL
k7eeel-0.1.0.dist-info/RECORD
